{
  "AWSTemplateFormatVersion": "2010-09-09",
  "Description": "The AWS CloudFormation template for this Serverless application",
  "Resources": {
    "ServerlessDeploymentBucket": {
      "Type": "AWS::S3::Bucket",
      "Properties": {
        "BucketEncryption": {
          "ServerSideEncryptionConfiguration": [
            {
              "ServerSideEncryptionByDefault": {
                "SSEAlgorithm": "AES256"
              }
            }
          ]
        }
      }
    },
    "ServerlessDeploymentBucketPolicy": {
      "Type": "AWS::S3::BucketPolicy",
      "Properties": {
        "Bucket": {
          "Ref": "ServerlessDeploymentBucket"
        },
        "PolicyDocument": {
          "Statement": [
            {
              "Action": "s3:*",
              "Effect": "Deny",
              "Principal": "*",
              "Resource": [
                {
                  "Fn::Join": [
                    "",
                    [
                      "arn:",
                      {
                        "Ref": "AWS::Partition"
                      },
                      ":s3:::",
                      {
                        "Ref": "ServerlessDeploymentBucket"
                      },
                      "/*"
                    ]
                  ]
                },
                {
                  "Fn::Join": [
                    "",
                    [
                      "arn:",
                      {
                        "Ref": "AWS::Partition"
                      },
                      ":s3:::",
                      {
                        "Ref": "ServerlessDeploymentBucket"
                      }
                    ]
                  ]
                }
              ],
              "Condition": {
                "Bool": {
                  "aws:SecureTransport": false
                }
              }
            }
          ]
        }
      }
    },
    "GetProductListLogGroup": {
      "Type": "AWS::Logs::LogGroup",
      "Properties": {
        "LogGroupName": "/aws/lambda/cloudx-backend-dev-getProductList"
      }
    },
    "GetProductsByIdLogGroup": {
      "Type": "AWS::Logs::LogGroup",
      "Properties": {
        "LogGroupName": "/aws/lambda/cloudx-backend-dev-getProductsById"
      }
    },
    "IamRoleLambdaExecution": {
      "Type": "AWS::IAM::Role",
      "Properties": {
        "AssumeRolePolicyDocument": {
          "Version": "2012-10-17",
          "Statement": [
            {
              "Effect": "Allow",
              "Principal": {
                "Service": [
                  "lambda.amazonaws.com"
                ]
              },
              "Action": [
                "sts:AssumeRole"
              ]
            }
          ]
        },
        "Policies": [
          {
            "PolicyName": {
              "Fn::Join": [
                "-",
                [
                  "cloudx-backend",
                  "dev",
                  "lambda"
                ]
              ]
            },
            "PolicyDocument": {
              "Version": "2012-10-17",
              "Statement": [
                {
                  "Effect": "Allow",
                  "Action": [
                    "logs:CreateLogStream",
                    "logs:CreateLogGroup",
                    "logs:TagResource"
                  ],
                  "Resource": [
                    {
                      "Fn::Sub": "arn:${AWS::Partition}:logs:${AWS::Region}:${AWS::AccountId}:log-group:/aws/lambda/cloudx-backend-dev*:*"
                    }
                  ]
                },
                {
                  "Effect": "Allow",
                  "Action": [
                    "logs:PutLogEvents"
                  ],
                  "Resource": [
                    {
                      "Fn::Sub": "arn:${AWS::Partition}:logs:${AWS::Region}:${AWS::AccountId}:log-group:/aws/lambda/cloudx-backend-dev*:*:*"
                    }
                  ]
                }
              ]
            }
          }
        ],
        "Path": "/",
        "RoleName": {
          "Fn::Join": [
            "-",
            [
              "cloudx-backend",
              "dev",
              {
                "Ref": "AWS::Region"
              },
              "lambdaRole"
            ]
          ]
        }
      }
    },
    "GetProductListLambdaFunction": {
      "Type": "AWS::Lambda::Function",
      "Properties": {
        "Code": {
          "S3Bucket": {
            "Ref": "ServerlessDeploymentBucket"
          },
          "S3Key": "serverless/cloudx-backend/dev/1696775989314-2023-10-08T14:39:49.314Z/cloudx-backend.zip"
        },
        "Handler": "handler.getProductList",
        "Runtime": "nodejs18.x",
        "FunctionName": "cloudx-backend-dev-getProductList",
        "MemorySize": 1024,
        "Timeout": 6,
        "Description": "Lambda function to retrieve a product list.",
        "Role": {
          "Fn::GetAtt": [
            "IamRoleLambdaExecution",
            "Arn"
          ]
        }
      },
      "DependsOn": [
        "GetProductListLogGroup"
      ]
    },
    "GetProductsByIdLambdaFunction": {
      "Type": "AWS::Lambda::Function",
      "Properties": {
        "Code": {
          "S3Bucket": {
            "Ref": "ServerlessDeploymentBucket"
          },
          "S3Key": "serverless/cloudx-backend/dev/1696775989314-2023-10-08T14:39:49.314Z/cloudx-backend.zip"
        },
        "Handler": "handler.getProductsById",
        "Runtime": "nodejs18.x",
        "FunctionName": "cloudx-backend-dev-getProductsById",
        "MemorySize": 1024,
        "Timeout": 6,
        "Description": "Retrieves a single product based on an id parameter.",
        "Role": {
          "Fn::GetAtt": [
            "IamRoleLambdaExecution",
            "Arn"
          ]
        }
      },
      "DependsOn": [
        "GetProductsByIdLogGroup"
      ]
    },
    "GetProductListLambdaVersionzLLrISJF6zClWKq6aQVTiuYq0gYf5peBWRXNtFmYC10": {
      "Type": "AWS::Lambda::Version",
      "DeletionPolicy": "Retain",
      "Properties": {
        "FunctionName": {
          "Ref": "GetProductListLambdaFunction"
        },
        "CodeSha256": "/O2HCNjTF/NMEM+31B/StB2HHvCOrs2ePjlPlW54A5c=",
        "Description": "Lambda function to retrieve a product list."
      }
    },
    "GetProductListLambdaFunctionUrl": {
      "Type": "AWS::Lambda::Url",
      "Properties": {
        "AuthType": "NONE",
        "TargetFunctionArn": {
          "Fn::GetAtt": [
            "GetProductListLambdaFunction",
            "Arn"
          ]
        }
      }
    },
    "GetProductListLambdaPermissionFnUrl": {
      "Type": "AWS::Lambda::Permission",
      "Properties": {
        "FunctionName": {
          "Fn::GetAtt": [
            "GetProductListLambdaFunction",
            "Arn"
          ]
        },
        "Action": "lambda:InvokeFunctionUrl",
        "Principal": "*",
        "FunctionUrlAuthType": "NONE"
      }
    },
    "GetProductsByIdLambdaVersionzOEg2q1LhLWpmNgICDoWqx4Uz1jADt849DeAUKW18lA": {
      "Type": "AWS::Lambda::Version",
      "DeletionPolicy": "Retain",
      "Properties": {
        "FunctionName": {
          "Ref": "GetProductsByIdLambdaFunction"
        },
        "CodeSha256": "/O2HCNjTF/NMEM+31B/StB2HHvCOrs2ePjlPlW54A5c=",
        "Description": "Retrieves a single product based on an id parameter."
      }
    },
    "GetProductsByIdLambdaFunctionUrl": {
      "Type": "AWS::Lambda::Url",
      "Properties": {
        "AuthType": "NONE",
        "TargetFunctionArn": {
          "Fn::GetAtt": [
            "GetProductsByIdLambdaFunction",
            "Arn"
          ]
        }
      }
    },
    "GetProductsByIdLambdaPermissionFnUrl": {
      "Type": "AWS::Lambda::Permission",
      "Properties": {
        "FunctionName": {
          "Fn::GetAtt": [
            "GetProductsByIdLambdaFunction",
            "Arn"
          ]
        },
        "Action": "lambda:InvokeFunctionUrl",
        "Principal": "*",
        "FunctionUrlAuthType": "NONE"
      }
    },
    "HttpApi": {
      "Type": "AWS::ApiGatewayV2::Api",
      "Properties": {
        "Name": "dev-cloudx-backend",
        "ProtocolType": "HTTP",
        "CorsConfiguration": {
          "AllowHeaders": [
            "Content-Type",
            "X-Amz-Date",
            "Authorization",
            "X-Api-Key",
            "X-Amz-Security-Token",
            "X-Amz-User-Agent",
            "X-Amzn-Trace-Id"
          ],
          "AllowMethods": [
            "OPTIONS",
            "GET"
          ],
          "AllowOrigins": [
            "*"
          ]
        }
      }
    },
    "HttpApiStage": {
      "Type": "AWS::ApiGatewayV2::Stage",
      "Properties": {
        "ApiId": {
          "Ref": "HttpApi"
        },
        "StageName": "$default",
        "AutoDeploy": true,
        "DefaultRouteSettings": {
          "DetailedMetricsEnabled": false
        }
      }
    },
    "GetProductListLambdaPermissionHttpApi": {
      "Type": "AWS::Lambda::Permission",
      "Properties": {
        "FunctionName": {
          "Fn::GetAtt": [
            "GetProductListLambdaFunction",
            "Arn"
          ]
        },
        "Action": "lambda:InvokeFunction",
        "Principal": "apigateway.amazonaws.com",
        "SourceArn": {
          "Fn::Join": [
            "",
            [
              "arn:",
              {
                "Ref": "AWS::Partition"
              },
              ":execute-api:",
              {
                "Ref": "AWS::Region"
              },
              ":",
              {
                "Ref": "AWS::AccountId"
              },
              ":",
              {
                "Ref": "HttpApi"
              },
              "/*"
            ]
          ]
        }
      }
    },
    "HttpApiIntegrationGetProductList": {
      "Type": "AWS::ApiGatewayV2::Integration",
      "Properties": {
        "ApiId": {
          "Ref": "HttpApi"
        },
        "IntegrationType": "AWS_PROXY",
        "IntegrationUri": {
          "Fn::GetAtt": [
            "GetProductListLambdaFunction",
            "Arn"
          ]
        },
        "PayloadFormatVersion": "2.0",
        "TimeoutInMillis": 30000
      }
    },
    "HttpApiRouteGetProducts": {
      "Type": "AWS::ApiGatewayV2::Route",
      "Properties": {
        "ApiId": {
          "Ref": "HttpApi"
        },
        "RouteKey": "GET /products",
        "Target": {
          "Fn::Join": [
            "/",
            [
              "integrations",
              {
                "Ref": "HttpApiIntegrationGetProductList"
              }
            ]
          ]
        }
      },
      "DependsOn": "HttpApiIntegrationGetProductList"
    },
    "GetProductsByIdLambdaPermissionHttpApi": {
      "Type": "AWS::Lambda::Permission",
      "Properties": {
        "FunctionName": {
          "Fn::GetAtt": [
            "GetProductsByIdLambdaFunction",
            "Arn"
          ]
        },
        "Action": "lambda:InvokeFunction",
        "Principal": "apigateway.amazonaws.com",
        "SourceArn": {
          "Fn::Join": [
            "",
            [
              "arn:",
              {
                "Ref": "AWS::Partition"
              },
              ":execute-api:",
              {
                "Ref": "AWS::Region"
              },
              ":",
              {
                "Ref": "AWS::AccountId"
              },
              ":",
              {
                "Ref": "HttpApi"
              },
              "/*"
            ]
          ]
        }
      }
    },
    "HttpApiIntegrationGetProductsById": {
      "Type": "AWS::ApiGatewayV2::Integration",
      "Properties": {
        "ApiId": {
          "Ref": "HttpApi"
        },
        "IntegrationType": "AWS_PROXY",
        "IntegrationUri": {
          "Fn::GetAtt": [
            "GetProductsByIdLambdaFunction",
            "Arn"
          ]
        },
        "PayloadFormatVersion": "2.0",
        "TimeoutInMillis": 30000
      }
    },
    "HttpApiRouteGetProductsProductidVar": {
      "Type": "AWS::ApiGatewayV2::Route",
      "Properties": {
        "ApiId": {
          "Ref": "HttpApi"
        },
        "RouteKey": "GET /products/{productId}",
        "Target": {
          "Fn::Join": [
            "/",
            [
              "integrations",
              {
                "Ref": "HttpApiIntegrationGetProductsById"
              }
            ]
          ]
        }
      },
      "DependsOn": "HttpApiIntegrationGetProductsById"
    }
  },
  "Outputs": {
    "ServerlessDeploymentBucketName": {
      "Value": {
        "Ref": "ServerlessDeploymentBucket"
      },
      "Export": {
        "Name": "sls-cloudx-backend-dev-ServerlessDeploymentBucketName"
      }
    },
    "GetProductListLambdaFunctionQualifiedArn": {
      "Description": "Current Lambda function version",
      "Value": {
        "Ref": "GetProductListLambdaVersionzLLrISJF6zClWKq6aQVTiuYq0gYf5peBWRXNtFmYC10"
      },
      "Export": {
        "Name": "sls-cloudx-backend-dev-GetProductListLambdaFunctionQualifiedArn"
      }
    },
    "GetProductListLambdaFunctionUrl": {
      "Description": "Lambda Function URL",
      "Value": {
        "Fn::GetAtt": [
          "GetProductListLambdaFunctionUrl",
          "FunctionUrl"
        ]
      },
      "Export": {
        "Name": "sls-cloudx-backend-dev-GetProductListLambdaFunctionUrl"
      }
    },
    "GetProductsByIdLambdaFunctionQualifiedArn": {
      "Description": "Current Lambda function version",
      "Value": {
        "Ref": "GetProductsByIdLambdaVersionzOEg2q1LhLWpmNgICDoWqx4Uz1jADt849DeAUKW18lA"
      },
      "Export": {
        "Name": "sls-cloudx-backend-dev-GetProductsByIdLambdaFunctionQualifiedArn"
      }
    },
    "GetProductsByIdLambdaFunctionUrl": {
      "Description": "Lambda Function URL",
      "Value": {
        "Fn::GetAtt": [
          "GetProductsByIdLambdaFunctionUrl",
          "FunctionUrl"
        ]
      },
      "Export": {
        "Name": "sls-cloudx-backend-dev-GetProductsByIdLambdaFunctionUrl"
      }
    },
    "HttpApiId": {
      "Description": "Id of the HTTP API",
      "Value": {
        "Ref": "HttpApi"
      },
      "Export": {
        "Name": "sls-cloudx-backend-dev-HttpApiId"
      }
    },
    "HttpApiUrl": {
      "Description": "URL of the HTTP API",
      "Value": {
        "Fn::Join": [
          "",
          [
            "https://",
            {
              "Ref": "HttpApi"
            },
            ".execute-api.",
            {
              "Ref": "AWS::Region"
            },
            ".",
            {
              "Ref": "AWS::URLSuffix"
            }
          ]
        ]
      },
      "Export": {
        "Name": "sls-cloudx-backend-dev-HttpApiUrl"
      }
    }
  }
}